LICENSE
README.rst
setup.py
control/action.py
control/filter.py
control/jobber.py
logic/behavior.py
plugin2cube/__init__.py
plugin2cube/__main__.py
plugin2cube/plugin2cube.py
plugin2cube.egg-info/PKG-INFO
plugin2cube.egg-info/SOURCES.txt
plugin2cube.egg-info/dependency_links.txt
plugin2cube.egg-info/entry_points.txt
plugin2cube.egg-info/requires.txt
plugin2cube.egg-info/top_level.txt
state/data.py
tests/test_example.py