Metadata-Version: 2.1
Name: plugin2cube
Version: 2.2.14
Summary: A ChRIS helper app that registers a plugin to a CUBE instance
Home-page: https://github.com/FNNDSC/plugin2cube
Author: FNNDSC
Author-email: rudolph.pienaar@childrens.harvard.edu
License: MIT
Classifier: License :: OSI Approved :: MIT License
Classifier: Topic :: Scientific/Engineering
Classifier: Topic :: Scientific/Engineering :: Bio-Informatics
Classifier: Topic :: Scientific/Engineering :: Medical Science Apps.
License-File: LICENSE
Requires-Dist: pudb
Requires-Dist: loguru
Requires-Dist: python-chrisclient
Provides-Extra: none
Provides-Extra: dev
Requires-Dist: pytest~=7.1; extra == "dev"
Requires-Dist: pytest-mock~=3.8; extra == "dev"
